vidurl/__init__.py
vidurl/__main__.py
vidurl/cli.py
vidurl/config.py
vidurl/exceptions.py
vidurl/extractor.py
vidurl/utils.py
vidurl-0.1.0.dist-info/licenses/LICENSE
vidurl-0.1.0.dist-info/METADATA
vidurl-0.1.0.dist-info/WHEEL
vidurl-0.1.0.dist-info/entry_points.txt
vidurl-0.1.0.dist-info/top_level.txt
vidurl-0.1.0.dist-info/RECORD
