Metadata-Version: 2.4
Name: vidurl
Version: 0.1.0
Summary: Extract video URLs from web pages and generate curl download commands
Author: vidurl contributors
Maintainer: vidurl contributors
License: GPL-2.0-or-later
Project-URL: Homepage, https://github.com/gfrmin/vidurl
Project-URL: Repository, https://github.com/gfrmin/vidurl.git
Project-URL: Issues, https://github.com/gfrmin/vidurl/issues
Keywords: video,url,extractor,selenium,curl,download,web-scraping
Classifier: Development Status :: 4 - Beta
Classifier: Environment :: Console
Classifier: Intended Audience :: Developers
Classifier: Intended Audience :: End Users/Desktop
Classifier: License :: OSI Approved :: GNU General Public License v2 or later (GPLv2+)
Classifier: Operating System :: OS Independent
Classifier: Programming Language :: Python :: 3
Classifier: Programming Language :: Python :: 3.13
Classifier: Programming Language :: Python :: 3 :: Only
Classifier: Topic :: Internet :: WWW/HTTP
Classifier: Topic :: Multimedia :: Video
Classifier: Topic :: Software Development :: Libraries :: Python Modules
Classifier: Topic :: Utilities
Requires-Python: >=3.13
License-File: LICENSE
Requires-Dist: beautifulsoup4>=4.13.5
Requires-Dist: requests>=2.32.5
Requires-Dist: selenium>=4.35.0
Provides-Extra: dev
Requires-Dist: pytest>=7.0; extra == "dev"
Requires-Dist: pytest-cov>=4.0; extra == "dev"
Requires-Dist: black>=23.0; extra == "dev"
Requires-Dist: isort>=5.12; extra == "dev"
Requires-Dist: flake8>=6.0; extra == "dev"
Dynamic: license-file
